Utils/__init__.py
Utils/connect/__init__.py
Utils/connect/mongo_conn.py
Utils/connect/rabbit_conn.py
Utils/connect/redis_conn.py
Utils/crawler/Forge.py
Utils/crawler/__init__.py
Utils/crawler/function.py
Utils/crawler/init.py
Utils/crawler/middleware.py
Utils/crawler/proxy.py
Utils/crawler/save_xls.py
Utils/crawler/scheduler.py
AdyanUtils-0.8.6.dist-info/LICENSE
AdyanUtils-0.8.6.dist-info/METADATA
AdyanUtils-0.8.6.dist-info/WHEEL
AdyanUtils-0.8.6.dist-info/top_level.txt
AdyanUtils-0.8.6.dist-info/RECORD
