Metadata-Version: 2.1
Name: AdyanUtils
Version: 0.8.6
Summary: Special package
Home-page: https://gitee.com/liujiang99/AdyanUtils
Author: Adyan
Author-email: 228923910@qq.com
License: UNKNOWN
Platform: UNKNOWN
Classifier: Programming Language :: Python :: 3
Classifier: License :: OSI Approved :: MIT License
Classifier: Operating System :: OS Independent
Requires-Python: >=3.7
License-File: LICENSE
Requires-Dist: requests (==2.27.1)
Requires-Dist: Faker (==13.2.0)
Requires-Dist: Scrapy (==2.5.1)
Requires-Dist: scrapy-redis (==0.7.2)
Requires-Dist: Twisted (==22.1.0)
Requires-Dist: gerapy-pyppeteer (==0.2.4)
Requires-Dist: pytz (==2021.3)
Requires-Dist: xlrd (==2.0.1)
Requires-Dist: xlutils (==2.0.0)
Requires-Dist: xlwt (==1.3.0)
Requires-Dist: pymongo (==3.6.0)
Requires-Dist: pika (==1.2.0)
Requires-Dist: redis (==4.1.4)
Requires-Dist: PyMuPDF (==1.22.5)
Requires-Dist: pytesseract (==0.3.10)
Requires-Dist: Pillow (==10.0.0)
Requires-Dist: cpca (==0.5.5)
